{
  "zwierzeta": [
    {
      "title": "Zolwie i krokodyle",
      "time": "21sec",
      "description": "poetry",
      "level": "3-4",
      "file":"my-story-tel/public/Zolwie i krokodyle.m4a"
    },
    {
      "title":"Pan zajac",
      "time": "",
      "description": "test",
      "level": "5-6",
      "file": "my-story-tel/public/Pan zając-zwierz.m4a"
    }
  ],
  "edukacyjne": [
    {
      "title": "Cudowne lekarstwo",
      "time": "21sec",
      "description": "poetry",
      "level": "3-4",
      "file":"my-story-tel/public/Cudowne lekarstwo-edu.m4a"
    },
    {
      "title":"Wrozka Marta",
      "time": "",
      "description": "test",
      "level": "3-4",
      "file": "my-story-tel/public/Marta-edu.m4a"
    }
    ],
    "czarodziejskie": [
      {
        "title": "3krasnoludki cz.I",
        "time": "21sec",
        "description": "poetry",
        "level": "3-4",
        "file":""
      },
      {
        "title":"Krasnoludki cz.2",
        "time": "",
        "description": "test",
        "level": "3-4",
        "file": ""
      }
  ]
}